syenv/__init__.py
syenv/exceptions.py
syenv/syenv.py
syenv-1.2.1.dist-info/LICENCE
syenv-1.2.1.dist-info/METADATA
syenv-1.2.1.dist-info/WHEEL
syenv-1.2.1.dist-info/top_level.txt
syenv-1.2.1.dist-info/RECORD
