Metadata-Version: 2.1
Name: syenv
Version: 1.2.1
Summary: A simple environment variables importer which some cool functionnalities
Home-page: https://github.com/Arthuchaut/syenv
Author: Arthuchaut
Author-email: arthuchaut@gmail.com
License: UNKNOWN
Platform: UNKNOWN
Classifier: Programming Language :: Python :: 3
Classifier: License :: OSI Approved :: MIT License
Classifier: Operating System :: OS Independent
Requires-Python: >=3.8
